README.md
setup.py
fitch/__init__.py
fitch/config.py
fitch/detector.py
fitch/device.py
fitch/logger.py
fitch/player.py
fitch/testcase.py
fitch/utils.py
fitch.egg-info/PKG-INFO
fitch.egg-info/SOURCES.txt
fitch.egg-info/dependency_links.txt
fitch.egg-info/requires.txt
fitch.egg-info/top_level.txt