Metadata-Version: 1.0
Name: fitch
Version: 0.4.2
Summary: Android UI automation based on opencv
Home-page: https://github.com/williamfzc/fitch
Author: williamfzc
Author-email: fengzc@vip.qq.com
License: UNKNOWN
Platform: UNKNOWN
